product/__init__.py
product/tools/__init__.py
product/tools/product_api_tool.py
product/tools/utils.py
product/yamls/product_api_tool.yaml
tests/__init__.py
tests/test_product_api_tool.py
product_intelligence_flow-0.0.3.dist-info/METADATA
product_intelligence_flow-0.0.3.dist-info/WHEEL
product_intelligence_flow-0.0.3.dist-info/entry_points.txt
product_intelligence_flow-0.0.3.dist-info/top_level.txt
product_intelligence_flow-0.0.3.dist-info/RECORD
