Metadata-Version: 2.1
Name: product_intelligence_flow
Version: 0.0.3
Summary: This is Product Intelligence prompt flow
